LICENSE.txt
MANIFEST.in
README.rst
requirements.txt
setup.cfg
setup.py
pyscripts/__init__.py
pyscripts/deps.py
pyscripts/display.py
pyscripts/parsers.py
pyscripts/version.py
pyscripts.egg-info/PKG-INFO
pyscripts.egg-info/SOURCES.txt
pyscripts.egg-info/dependency_links.txt
pyscripts.egg-info/requires.txt
pyscripts.egg-info/top_level.txt