Metadata-Version: 1.0
Name: pyscripts
Version: 0.0.0.dev3
Summary: Tools to work with python scripts
Home-page: UNKNOWN
Author: UNKNOWN
Author-email: UNKNOWN
License: UNKNOWN
Keywords: physics hep pyscripts
Platform: UNKNOWN
